{
	"Theme": 1,
	"BackgroundType": 2,
	"BackgroundColor": {
		"A": 100,
		"R": 255,
		"G": 255,
		"B": 255
	},
	"TextColor": {
		"A": 255,
		"R": 0,
		"G": 0,
		"B": 0
	},
	"SelectionColor": {
		"A": 100,
		"R": 100,
		"G": 100,
		"B": 150
	},

	"LineNumberColor": {
		"A": 100,
		"R": 150,
		"G": 150,
		"B": 150
	},
	"LineNumberBackground": {
		"A": 0,
		"R": 0,
		"G": 0,
		"B": 0
	},
	"LineHighlighterBackground": {
		"A": 50,
		"R": 180,
		"G": 180,
		"B": 180
	},
	"TextboxBackgroundType": 2,
	"TextBoxBackground": {
		"A": 0,
		"R": 0,
		"G": 0,
		"B": 0
	},
	"CursorColor": {
		"A": 255,
		"R": 0,
		"G": 0,
		"B": 0
	},
	"SearchHighlightColor": {
		"A": 150,
		"R": 255,
		"G": 150,
		"B": 0
	},
	"SelectedTabPageHeaderTextColor": {
		"A": 255,
		"R": 0,
		"G": 0,
		"B": 0
	},
	"UnSelectedTabPageHeaderTextColor": {
		"A": 150,
		"R": 0,
		"G": 0,
		"B": 0
	},
	"UnselectedTabPageHeaderBackground": {
		"A": 0,
		"R": 0,
		"G": 0,
		"B": 0
	},
	"SelectedTabPageHeaderBackground": {
		"A": 20,
		"R": 50,
		"G": 50,
		"B": 50
	},
	"StatusbarTextColor": {
		"A": 255,
		"R": 0,
		"G": 0,
		"B": 0
	},
	"StatusbarBackgroundColor": {
		"A": 255,
		"R": 245,
		"G": 245,
		"B": 245
	},
	"DialogBackgroundColor": {
		"A": 255,
		"R": 255,
		"G": 255,
		"B": 255
	},
	"DialogTextColor": {
		"A": 255,
		"R": 0,
		"G": 0,
		"B": 0
	},
	"DialogBackgroundType": 0
}